htfpaxer-1.4.dist-info/licenses/LICENSE.txt
paxer/cli.py
paxer/parser.py
paxer/stage.py
paxer/core/__init__.py
paxer/core/packer.py
paxer/core/paxed.py
paxer/core/stage.py
htfpaxer-1.4.dist-info/METADATA
htfpaxer-1.4.dist-info/WHEEL
htfpaxer-1.4.dist-info/entry_points.txt
htfpaxer-1.4.dist-info/top_level.txt
htfpaxer-1.4.dist-info/RECORD
