Metadata-Version: 2.4
Name: htfpaxer
Version: 1.4
License-File: LICENSE.txt
Requires-Dist: colorama
Requires-Dist: htfbox
Dynamic: license-file
